{
  "Software Engineer": "IT",
  "Systems Administrator": "IT",
  "Network Engineer": "IT",
  "DevOps Engineer": "IT",
  "IT Support Specialist": "IT",
  "Database Administrator": "IT",
  "Cloud Architect": "IT",
  "Full Stack Developer": "IT",
  "Front End Developer": "IT",
  "Back End Developer": "IT",
  "IT Manager": "IT",
  "Technical Support Engineer": "IT",
  "Infrastructure Engineer": "IT",
  "Site Reliability Engineer": "IT",
  "QA Engineer": "IT",
  "Accountant": "Finance",
  "Financial Analyst": "Finance",
  "Controller": "Finance",
  "Chief Financial Officer": "Finance",
  "Bookkeeper": "Finance",
  "Tax Accountant": "Finance",
  "Accounts Payable Specialist": "Finance",
  "Accounts Receivable Specialist": "Finance",
  "Financial Manager": "Finance",
  "Budget Analyst": "Finance",
  "Payroll Specialist": "Finance",
  "Auditor": "Finance",
  "Treasury Analyst": "Finance",
  "Financial Planning Analyst": "Finance",
  "Mechanical Engineer": "Engineering",
  "Electrical Engineer": "Engineering",
  "Civil Engineer": "Engineering",
  "Chemical Engineer": "Engineering",
  "Industrial Engineer": "Engineering",
  "Manufacturing Engineer": "Engineering",
  "Process Engineer": "Engineering",
  "Quality Engineer": "Engineering",
  "Structural Engineer": "Engineering",
  "Project Engineer": "Engineering",
  "Design Engineer": "Engineering",
  "Automation Engineer": "Engineering",
  "Test Engineer": "Engineering",
  "Systems Engineer": "Engineering",
  "Reliability Engineer": "Engineering",
  "Marketing Manager": "Marketing",
  "Digital Marketing Specialist": "Marketing",
  "Content Marketing Manager": "Marketing",
  "Social Media Manager": "Marketing",
  "Brand Manager": "Marketing",
  "Marketing Coordinator": "Marketing",
  "SEO Specialist": "Marketing",
  "Email Marketing Specialist": "Marketing",
  "Product Marketing Manager": "Marketing",
  "Marketing Analyst": "Marketing",
  "Public Relations Manager": "Marketing",
  "Growth Marketing Manager": "Marketing",
  "Marketing Director": "Marketing",
  "Demand Generation Manager": "Marketing",
  "HR Manager": "Human Resources",
  "HR Generalist": "Human Resources",
  "Recruiter": "Human Resources",
  "Talent Acquisition Specialist": "Human Resources",
  "HR Business Partner": "Human Resources",
  "Compensation and Benefits Manager": "Human Resources",
  "HR Coordinator": "Human Resources",
  "Training and Development Manager": "Human Resources",
  "Employee Relations Specialist": "Human Resources",
  "HR Director": "Human Resources",
  "Payroll Manager": "Human Resources",
  "Onboarding Specialist": "Human Resources",
  "HRIS Analyst": "Human Resources",
  "Customer Service Representative": "Customer Service",
  "Customer Success Manager": "Customer Service",
  "Customer Support Specialist": "Customer Service",
  "Client Services Manager": "Customer Service",
  "Customer Experience Manager": "Customer Service",
  "Account Manager": "Customer Service",
  "Customer Service Manager": "Customer Service",
  "Technical Support Representative": "Customer Service",
  "Customer Care Specialist": "Customer Service",
  "Customer Service Supervisor": "Customer Service",
  "Call Center Agent": "Call Center",
  "Call Center Supervisor": "Call Center",
  "Call Center Manager": "Call Center",
  "Inbound Sales Representative": "Call Center",
  "Outbound Sales Representative": "Call Center",
  "Call Center Quality Analyst": "Call Center",
  "Telemarketer": "Call Center",
  "Call Center Team Leader": "Call Center",
  "Call Center Trainer": "Call Center",
  "Restaurant Manager": "Food Service",
  "Chef": "Food Service",
  "Line Cook": "Food Service",
  "Server": "Food Service",
  "Bartender": "Food Service",
  "Food Service Worker": "Food Service",
  "Kitchen Manager": "Food Service",
  "Sous Chef": "Food Service",
  "Prep Cook": "Food Service",
  "Host/Hostess": "Food Service",
  "Barista": "Food Service",
  "Catering Manager": "Food Service",
  "Food Runner": "Food Service",
  "Safety Manager": "Health and Safety",
  "Environmental Health and Safety Specialist": "Health and Safety",
  "Occupational Health and Safety Specialist": "Health and Safety",
  "Safety Coordinator": "Health and Safety",
  "Industrial Hygienist": "Health and Safety",
  "Safety Director": "Health and Safety",
  "Risk Manager": "Health and Safety",
  "Safety Engineer": "Health and Safety",
  "Compliance Officer": "Health and Safety",
  "Emergency Management Specialist": "Health and Safety",
  "Registered Nurse": "Healthcare",
  "Physician": "Healthcare",
  "Medical Assistant": "Healthcare",
  "Nurse Practitioner": "Healthcare",
  "Physician Assistant": "Healthcare",
  "Physical Therapist": "Healthcare",
  "Occupational Therapist": "Healthcare",
  "Radiologic Technologist": "Healthcare",
  "Pharmacist": "Healthcare",
  "Pharmacy Technician": "Healthcare",
  "Respiratory Therapist": "Healthcare",
  "Clinical Lab Technician": "Healthcare",
  "Dental Hygienist": "Healthcare",
  "Medical Records Specialist": "Healthcare",
  "Healthcare Administrator": "Healthcare",
  "Data Analyst": "Data and Analytics",
  "Data Scientist": "Data and Analytics",
  "Business Intelligence Analyst": "Data and Analytics",
  "Data Engineer": "Data and Analytics",
  "Analytics Manager": "Data and Analytics",
  "Machine Learning Engineer": "Data and Analytics",
  "Quantitative Analyst": "Data and Analytics",
  "Business Analyst": "Data and Analytics",
  "Data Architect": "Data and Analytics",
  "Research Analyst": "Data and Analytics",
  "Statistical Analyst": "Data and Analytics",
  "Analytics Engineer": "Data and Analytics",
  "Librarian": "Library",
  "Library Assistant": "Library",
  "Reference Librarian": "Library",
  "Library Director": "Library",
  "Archivist": "Library",
  "Library Technician": "Library",
  "Circulation Manager": "Library",
  "Cataloger": "Library",
  "Attorney": "Legal",
  "Paralegal": "Legal",
  "Legal Assistant": "Legal",
  "Corporate Counsel": "Legal",
  "Contract Manager": "Legal",
  "Legal Secretary": "Legal",
  "Litigation Attorney": "Legal",
  "General Counsel": "Legal",
  "Legal Operations Manager": "Legal",
  "Patent Attorney": "Legal",
  "Intellectual Property Attorney": "Legal",
  "Project Manager": "Project Management",
  "Program Manager": "Project Management",
  "Project Coordinator": "Project Management",
  "Scrum Master": "Project Management",
  "Agile Coach": "Project Management",
  "PMO Director": "Project Management",
  "Portfolio Manager": "Project Management",
  "Project Controls Specialist": "Project Management",
  "Project Scheduler": "Project Management",
  "Technical Project Manager": "Project Management",
  "Research Scientist": "Research",
  "Research Associate": "Research",
  "Clinical Research Coordinator": "Research",
  "Market Research Analyst": "Research",
  "Research Assistant": "Research",
  "Principal Scientist": "Research",
  "Research Manager": "Research",
  "Laboratory Technician": "Research",
  "User Researcher": "Research",
  "Research Director": "Research",
  "Security Guard": "Physical Security",
  "Security Manager": "Physical Security",
  "Security Officer": "Physical Security",
  "Loss Prevention Specialist": "Physical Security",
  "Security Director": "Physical Security",
  "Security Supervisor": "Physical Security",
  "Security Analyst": "Physical Security",
  "Security Consultant": "Physical Security",
  "Warehouse Associate": "Warehouse",
  "Warehouse Manager": "Warehouse",
  "Forklift Operator": "Warehouse",
  "Shipping and Receiving Clerk": "Warehouse",
  "Inventory Control Specialist": "Warehouse",
  "Warehouse Supervisor": "Warehouse",
  "Material Handler": "Warehouse",
  "Picker/Packer": "Warehouse",
  "Logistics Coordinator": "Warehouse",
  "Warehouse Operations Manager": "Warehouse",
  "Cybersecurity Analyst": "Cybersecurity",
  "Information Security Manager": "Cybersecurity",
  "Security Engineer": "Cybersecurity",
  "Penetration Tester": "Cybersecurity",
  "Security Architect": "Cybersecurity",
  "Chief Information Security Officer": "Cybersecurity",
  "Security Operations Center Analyst": "Cybersecurity",
  "Incident Response Analyst": "Cybersecurity",
  "Threat Intelligence Analyst": "Cybersecurity",
  "Identity and Access Management Specialist": "Cybersecurity",
  "Cybersecurity Consultant": "Cybersecurity",
  "Security Compliance Analyst": "Cybersecurity",
  "Teacher": "Education",
  "School Principal": "Education",
  "Instructional Coordinator": "Education",
  "School Counselor": "Education",
  "Special Education Teacher": "Education",
  "Curriculum Developer": "Education",
  "Academic Advisor": "Education",
  "Teaching Assistant": "Education",
  "Professor": "Education",
  "Assistant Principal": "Education",
  "Education Administrator": "Education",
  "Instructional Designer": "Education",
  "Tutor": "Education",
  "Biotechnology Research Scientist": "BioTech",
  "Bioinformatics Scientist": "BioTech",
  "Clinical Research Associate": "BioTech",
  "Bioprocess Engineer": "BioTech",
  "Regulatory Affairs Specialist": "BioTech",
  "Quality Control Analyst": "BioTech",
  "Laboratory Manager": "BioTech",
  "Biomedical Engineer": "BioTech",
  "Research and Development Scientist": "BioTech",
  "Manufacturing Technician": "BioTech",
  "Validation Specialist": "BioTech",
  "Sales Representative": "Sales",
  "Account Executive": "Sales",
  "Sales Manager": "Sales",
  "Business Development Manager": "Sales",
  "Inside Sales Representative": "Sales",
  "Sales Engineer": "Sales",
  "Territory Sales Manager": "Sales",
  "Regional Sales Manager": "Sales",
  "Sales Director": "Sales",
  "Vice President of Sales": "Sales",
  "Sales Operations Manager": "Sales",
  "Enterprise Account Executive": "Sales",
  "Channel Sales Manager": "Sales",
  "Sales Development Representative": "Sales",
  "Operations Manager": "Operations",
  "Operations Coordinator": "Operations",
  "Supply Chain Manager": "Operations",
  "Logistics Manager": "Operations",
  "Operations Director": "Operations",
  "Process Improvement Manager": "Operations",
  "Operations Analyst": "Operations",
  "Production Manager": "Operations",
  "Chief Operating Officer": "Operations",
  "Business Operations Manager": "Operations",
  "Procurement Manager": "Operations",
  "Operations Supervisor": "Operations",
  "Product Manager": "Product Management",
  "Senior Product Manager": "Product Management",
  "Product Owner": "Product Management",
  "Director of Product Management": "Product Management",
  "Associate Product Manager": "Product Management",
  "Technical Product Manager": "Product Management",
  "Chief Product Officer": "Product Management",
  "Vice President of Product": "Product Management",
  "Product Operations Manager": "Product Management",
  "UX Designer": "Design",
  "UI Designer": "Design",
  "Graphic Designer": "Design",
  "Product Designer": "Design",
  "Creative Director": "Design",
  "Art Director": "Design",
  "UX Researcher": "Design",
  "Visual Designer": "Design",
  "Motion Graphics Designer": "Design",
  "Interaction Designer": "Design",
  "Design Director": "Design",
  "Brand Designer": "Design",
  "Administrative Assistant": "Administrative",
  "Executive Assistant": "Administrative",
  "Office Manager": "Administrative",
  "Receptionist": "Administrative",
  "Secretary": "Administrative",
  "Office Administrator": "Administrative",
  "Data Entry Clerk": "Administrative",
  "Administrative Coordinator": "Administrative",
  "Office Coordinator": "Administrative",
  "Executive Secretary": "Administrative",
  "Facilities Manager": "Facilities",
  "Maintenance Technician": "Facilities",
  "Building Engineer": "Facilities",
  "Facilities Coordinator": "Facilities",
  "Custodian": "Facilities",
  "Groundskeeper": "Facilities",
  "Facilities Director": "Facilities",
  "HVAC Technician": "Facilities",
  "Property Manager": "Facilities",
  "Retail Sales Associate": "Retail",
  "Store Manager": "Retail",
  "Assistant Store Manager": "Retail",
  "Cashier": "Retail",
  "Merchandiser": "Retail",
  "Retail Buyer": "Retail",
  "Visual Merchandiser": "Retail",
  "Stock Associate": "Retail",
  "Sales Floor Supervisor": "Retail",
  "District Manager": "Retail",
  "Electrician": "Skilled Trades",
  "Plumber": "Skilled Trades",
  "HVAC Technician": "Skilled Trades",
  "Carpenter": "Skilled Trades",
  "Welder": "Skilled Trades",
  "Mechanic": "Skilled Trades",
  "Pipefitter": "Skilled Trades",
  "Millwright": "Skilled Trades",
  "Construction Worker": "Skilled Trades",
  "Heavy Equipment Operator": "Skilled Trades",
  "Maintenance Mechanic": "Skilled Trades",
  "Truck Driver": "Transportation",
  "Delivery Driver": "Transportation",
  "Dispatcher": "Transportation",
  "Transportation Manager": "Transportation",
  "Fleet Manager": "Transportation",
  "Route Driver": "Transportation",
  "Freight Coordinator": "Transportation",
  "Driver Supervisor": "Transportation",
  "Production Worker": "Manufacturing",
  "Production Supervisor": "Manufacturing",
  "Assembly Line Worker": "Manufacturing",
  "CNC Machinist": "Manufacturing",
  "Quality Inspector": "Manufacturing",
  "Production Planner": "Manufacturing",
  "Plant Manager": "Manufacturing",
  "Manufacturing Technician": "Manufacturing",
  "Machine Operator": "Manufacturing",
  "Chief Executive Officer": "Executive",
  "Chief Technology Officer": "Executive",
  "Chief Marketing Officer": "Executive",
  "Chief Human Resources Officer": "Executive",
  "Chief Information Officer": "Executive",
  "Managing Director": "Executive",
  "President": "Executive",
  "Vice President": "Executive"
}